scarf/__init__.py
scarf/ann.py
scarf/assay.py
scarf/bio_data.py
scarf/dendrogram.py
scarf/downloader.py
scarf/feat_utils.py
scarf/harmony.py
scarf/knn_utils.py
scarf/mapping_utils.py
scarf/markers.py
scarf/meld_assay.py
scarf/merge.py
scarf/metadata.py
scarf/metrics.py
scarf/plots.py
scarf/readers.py
scarf/umap.py
scarf/utils.py
scarf/writers.py
scarf/datastore/__init__.py
scarf/datastore/base_datastore.py
scarf/datastore/datastore.py
scarf/datastore/graph_datastore.py
scarf/datastore/mapping_datastore.py
scarf-0.32.2.data/scripts/sgtsne
scarf-0.32.2.dist-info/licenses/LICENSE
scarf-0.32.2.dist-info/METADATA
scarf-0.32.2.dist-info/WHEEL
scarf-0.32.2.dist-info/top_level.txt
scarf-0.32.2.dist-info/RECORD
