Metadata-Version: 2.4
Name: scarf
Version: 0.32.2
Summary: Scarf: A scalable tool for single-cell omics data analysis
Home-page: https://github.com/parashardhapola/scarf
Author: Parashar Dhapola
Author-email: parashar.dhapola@gmail.com
License: BSD 3-Clause
Keywords: single-cell
Classifier: Development Status :: 4 - Beta
Classifier: License :: OSI Approved :: BSD License
Classifier: Natural Language :: English
Classifier: Programming Language :: Python :: 3
Classifier: Programming Language :: Python :: 3.12
Requires-Python: >=3.11
License-File: LICENSE
Requires-Dist: dask[array]<=2024.7.1
Requires-Dist: h5py>=3.3.0
Requires-Dist: hnswlib==0.8.0
Requires-Dist: importlib_metadata
Requires-Dist: joblib
Requires-Dist: leidenalg
Requires-Dist: loguru
Requires-Dist: networkx==3.4.2
Requires-Dist: numba<=0.61.2
Requires-Dist: numcodecs<0.16
Requires-Dist: numpy==1.26.4
Requires-Dist: packaging
Requires-Dist: pandas
Requires-Dist: polars<=1.25
Requires-Dist: pyarrow
Requires-Dist: scikit-learn==1.6.1
Requires-Dist: scikit-network<=0.33.2
Requires-Dist: scipy==1.15.2
Requires-Dist: setuptools
Requires-Dist: statsmodels
Requires-Dist: threadpoolctl
Requires-Dist: tqdm
Requires-Dist: umap-learn
Requires-Dist: zarr<=2.16.0
Provides-Extra: extra
Requires-Dist: requests; extra == "extra"
Requires-Dist: gensim; extra == "extra"
Requires-Dist: kneed; extra == "extra"
Requires-Dist: matplotlib; extra == "extra"
Requires-Dist: seaborn; extra == "extra"
Requires-Dist: cmocean; extra == "extra"
Requires-Dist: datashader; extra == "extra"
Requires-Dist: ipython-autotime; extra == "extra"
Requires-Dist: ipywidgets; extra == "extra"
Dynamic: author
Dynamic: author-email
Dynamic: classifier
Dynamic: description
Dynamic: description-content-type
Dynamic: home-page
Dynamic: keywords
Dynamic: license
Dynamic: license-file
Dynamic: provides-extra
Dynamic: requires-dist
Dynamic: requires-python
Dynamic: summary
